LICENSE
MANIFEST.in
README.rst
ns4600.py
setup.py
ns4600.egg-info/PKG-INFO
ns4600.egg-info/SOURCES.txt
ns4600.egg-info/dependency_links.txt
ns4600.egg-info/top_level.txt