Metadata-Version: 1.0
Name: ns4600
Version: 1.0.0
Summary: Control the Promise SmartStor NS4600 NAS server
Home-page: https://github.com/rholder/ns4600
Author: Ray Holder
Author-email: UNKNOWN
License: UNKNOWN
Platform: UNKNOWN
Classifier: Intended Audience :: Developers
Classifier: Natural Language :: English
Classifier: License :: OSI Approved :: Apache Software License
Classifier: Programming Language :: Python
Classifier: Programming Language :: Python :: 2.6
Classifier: Programming Language :: Python :: 2.7
